adsocket/__init__.py
adsocket/http_handlers.py
adsocket/server.py
adsocket/test.py
adsocket/version.py
adsocket/conf/__init__.py
adsocket/conf/default_settings.py
adsocket/conf/dev_me.py
adsocket/core/__init__.py
adsocket/core/application.py
adsocket/core/auth.py
adsocket/core/channels.py
adsocket/core/decorators.py
adsocket/core/exceptions.py
adsocket/core/logging_setup.py
adsocket/core/message.py
adsocket/core/permissions.py
adsocket/core/services.py
adsocket/core/signals.py
adsocket/core/utils.py
adsocket/core/broker/__init__.py
adsocket/core/broker/redis.py
adsocket/core/commands/__init__.py
adsocket/core/commands/commands.py
adsocket/core/commands/exceptions.py
adsocket/ws/__init__.py
adsocket/ws/client.py
adsocket-0.2.2.dist-info/LICENSE
adsocket-0.2.2.dist-info/METADATA
adsocket-0.2.2.dist-info/WHEEL
adsocket-0.2.2.dist-info/entry_points.txt
adsocket-0.2.2.dist-info/top_level.txt
adsocket-0.2.2.dist-info/zip-safe
adsocket-0.2.2.dist-info/RECORD
