Metadata-Version: 2.1
Name: adsocket
Version: 0.2.2
Summary: Websocket protocol
Home-page: UNKNOWN
License: MIT
Platform: any
Classifier: Programming Language :: Python :: 3.7
Classifier: Programming Language :: Python :: 3.8
Classifier: License :: OSI Approved :: MIT License
Classifier: Operating System :: OS Independent
Classifier: Development Status :: 4 - Beta
License-File: LICENSE
Requires-Dist: aiohttp (>=3.6.2)
Requires-Dist: aioredis (>=2.0.0)
Requires-Dist: async-timeout (==3.0.1)
Requires-Dist: raven (==6.3.0)
Requires-Dist: uvloop (>=0.16.0)
